Workbook

Sheet Financial data
A1: Year | B1: Revenue | C1: Net profit | D1: EBITDA | E1: EPS (in INR) | F1: Total assets | G1: Total equity | H1: Total debt | I1: Total current assets | J1: Total current liabilities | K1: operating profit
A2: FY 2020 | B2: 70676 | C2: 11057 | D2: 17316 | E2: 40.75 | F2: 82819 | G2: 51267 | H2: 7986 | I2: =SUM(E10:E14) -> 37863 | J2: =SUM(M8:M10) -> 23412 | K2: 17316
A3: FY 2021 | B3: 75379 | C3: 11169 | D3: 20048 | E3: 41.07 | F3: 86047 | G3: 59913 | H3: 6864 | I3: =SUM(F10:F14) -> 41728 | J3: =SUM(N8:N10) -> 19101 | K3: 20048
A4: FY 2022 | B4: 85651 | C4: 13523 | D4: 20529 | E4: 49.74 | F4: 88921 | G4: 61914 | H4: 6343 | I4: =SUM(G10:G14) -> 47364 | J4: =SUM(O8:O10) -> 20572 | K4: 20529
A5: FY 2023 | B5: 101456 | C5: 14845 | D5: 22628 | E5: 54.73 | F5: 93250 | G5: 65405 | H5: 4794 | I5: =SUM(H10:H14) -> 53096 | J5: =SUM(P8:P10) -> 23058 | K5: 22628
A6: FY 2024 | B6: 109913 | C6: 15710 | D6: 24198 | E6: 57.86 | F6: 99006 | G6: 68293 | H6: 5758 | I6: =SUM(I10:I14) -> 56698 | J6: =SUM(Q8:Q10) -> 24977 | K6: 24198
M8: 1166 | N8: 5457 | O8: 6278 | P8: 6428 | Q8: 5853 | R8: 6225
M9: 252 | N9: 320 | O9: 222 | P9: 252 | Q9: 158 | R9: 204
E10: 91 | F10: 94 | G10: 161 | H10: 228 | I10: 185 | J10: 133 | M10: 21994 | N10: 13324 | O10: 14072 | P10: 16378 | Q10: 18966 | R10: 22102
E11: 14131 | F11: 17525 | G11: 20671 | H11: 25506 | I11: 25521 | J11: 25842
E12: 4976 | F12: 8888 | G12: 12636 | H12: 14724 | I12: 20150 | J12: 21289
E13: 1459 | F13: 1506 | G13: 1819 | H13: 1967 | I13: 2114 | J13: 2753
E14: 17206 | F14: 13715 | G14: 12077 | H14: 10671 | I14: 8728 | J14: 10668

Sheet Ratio analysis
A1: Ratio | B1: FY20 | C1: FY21 | D1: FY22 | E1: FY23 | F1: FY24
A2: ROE | B2: ='Financial data'!C2/'Financial data'!G2 -> 0.2156748 | C2: ='Financial data'!C3/'Financial data'!G3 -> 0.18642031 | D2: ='Financial data'!C4/'Financial data'!G4 -> 0.21841587 | E2: ='Financial data'!C5/'Financial data'!G5 -> 0.22697042 | F2: ='Financial data'!C6/'Financial data'!G6 -> 0.23003822
A3: ROCE | B3: ='Financial data'!K2/('Financial data'!F2-'Financial data'!J2) -> 0.2914808 | C3: ='Financial data'!K3/('Financial data'!F3-'Financial data'!J3) -> 0.29946524 | D3: ='Financial data'!K4/('Financial data'!F4-'Financial data'!J3) -> 0.2940275 | E3: ='Financial data'!K5/('Financial data'!F5-'Financial data'!J5) -> 0.32237292 | F3: ='Financial data'!K6/('Financial data'!F6-'Financial data'!J6) -> 0.3268719
A4: Asset turnover | B4: ='Financial data'!B2/'Financial data'!F2 -> 0.85337906 | C4: ='Financial data'!B3/'Financial data'!F3 -> 0.87602124 | D4: ='Financial data'!B4/'Financial data'!F4 -> 0.96322578 | E4: ='Financial data'!B5/'Financial data'!F5 -> 1.088 | F4: ='Financial data'!B6/'Financial data'!F6 -> 1.110165
A5: Current ratio | B5: ='Financial data'!I2/'Financial data'!J2 -> 1.6172476 | C5: ='Financial data'!I3/'Financial data'!J3 -> 2.1845977 | D5: ='Financial data'!I4/'Financial data'!J4 -> 2.3023527 | E5: ='Financial data'!I5/'Financial data'!J5 -> 2.3027149 | F5: ='Financial data'!I6/'Financial data'!J6 -> 2.2700084
A6: Debt to equity | B6: ='Financial data'!H2/'Financial data'!G2 -> 0.15577272 | C6: ='Financial data'!H3/'Financial data'!G3 -> 0.11456612 | D6: ='Financial data'!H4/'Financial data'!G4 -> 0.10244856 | E6: ='Financial data'!H5/'Financial data'!G5 -> 0.073297149 | F6: ='Financial data'!H6/'Financial data'!G6 -> 0.08431318

Sheet Shareholding pattern 
A1: Category | B1: FY20 | C1: FY21 | D1: FY22 | E1: FY23 | F1: FY24
A2: Promoters | B2: 0.6033 | C2: 0.6033 | D2: 0.6072 | E2: 0.6082 | F2: 0.6082
A3: FIIs | B3: 0.2642 | C3: 0.2414 | D3: 0.1897 | E3: 0.1892 | F3: 0.1965
A4: DIIs | B4: 0.0911 | C4: 0.1054 | D4: 0.1468 | E4: 0.1528 | F4: 0.1495
A5: Public | B5: 0.041 | C5: 0.0497 | D5: 0.0538 | E5: 0.0474 | F5: 0.0435

Sheet Valuation
A1: Particular | B1: Value
A2: LatestEPS | B2: ='Financial data'!E6 -> 57.86
A3: Industry P/E | B3: 23.03
A4: Intrinsic Value (= EPS × P/E) | B4: =B2*B3 -> 1332.5158
A5: Current Market Price (CMP) | B5: ₹ 1,436
A6: Recommendation | B6: =IF(B4>B5,"buy","sell") -> sell
